htmresearch_core/__init__.py
htmresearch_core/_experimental.so
htmresearch_core/dummy.so
htmresearch_core/experimental.py
htmresearch_core/proto/ApicalTiebreakTemporalMemoryProto.capnp
htmresearch_core/proto/__init__.py
htmresearch_core-0.0.3.dist-info/DESCRIPTION.rst
htmresearch_core-0.0.3.dist-info/METADATA
htmresearch_core-0.0.3.dist-info/RECORD
htmresearch_core-0.0.3.dist-info/WHEEL
htmresearch_core-0.0.3.dist-info/metadata.json
htmresearch_core-0.0.3.dist-info/top_level.txt
